[{"speaker":"SPEAKER_06","totalSegmentos":18,"segmentosSRT":[{"id":"47","startTime":376.4,"endTime":380.03,"text":"A dog's gotta eat shit! Little bastard!","speaker":"SPEAKER_06"},{"id":"48","startTime":380.74,"endTime":382.5,"text":"If you don't stop...","speaker":"SPEAKER_06"},{"id":"49","startTime":383.01,"endTime":386.84,"text":"we'll lose the little we have.","speaker":"SPEAKER_06"},{"id":"50","startTime":387.51,"endTime":390.04,"text":"Aren't you capable of anything else?","speaker":"SPEAKER_06"},{"id":"51","startTime":390.38,"endTime":392.41,"text":"Is gambling all you know?","speaker":"SPEAKER_06"},{"id":"52","startTime":393.05,"endTime":396.49,"text":"Of all you could have learned, bastard!","speaker":"SPEAKER_06"},{"id":"57","startTime":418.34,"endTime":420.11,"text":"Will you cut it out?","speaker":"SPEAKER_06"},{"id":"58","startTime":422.05,"endTime":424.45,"text":"- What'd he just say?\n- Nothing. Eat.","speaker":"SPEAKER_06"},{"id":"167","startTime":1067.32,"endTime":1069.16,"text":"Good.","speaker":"SPEAKER_06"},{"id":"168","startTime":1071.13,"endTime":1075.83,"text":"A gambling debt's a debt,\nand debts must be paid.","speaker":"SPEAKER_06"},{"id":"169","startTime":1077.87,"endTime":1080.17,"text":"Everyone's here today.","speaker":"SPEAKER_06"},{"id":"170","startTime":1080.34,"endTime":1082.64,"text":"So let's do what must be done.","speaker":"SPEAKER_06"},{"id":"175","startTime":1113.94,"endTime":1116.74,"text":"I thought I'd live my final days here.","speaker":"SPEAKER_06"},{"id":"176","startTime":1128.02,"endTime":1129.25,"text":"Fugui.","speaker":"SPEAKER_06"},{"id":"177","startTime":1130.22,"endTime":1133.38,"text":"Turtle spawn! I'll kill him!","speaker":"SPEAKER_06"},{"id":"178","startTime":1133.46,"endTime":1137.39,"text":"I'll cut him into pieces! I'll clobber him!","speaker":"SPEAKER_06"},{"id":"179","startTime":1137.46,"endTime":1139.33,"text":"I'll never forgive you!","speaker":"SPEAKER_06"},{"id":"449","startTime":3167.66,"endTime":3169.05,"text":"It's ready.","speaker":"SPEAKER_06"}]}]