[{"speaker":"SPEAKER_05","totalSegmentos":40,"segmentosSRT":[{"id":"557","startTime":3832.38,"endTime":3833.5,"text":"Well?","speaker":"SPEAKER_05"},{"id":"558","startTime":3833.81,"endTime":3835.3,"text":"I'm not going!","speaker":"SPEAKER_05"},{"id":"566","startTime":3874.95,"endTime":3876.71,"text":"Should we add chili?","speaker":"SPEAKER_05"},{"id":"567","startTime":3878.35,"endTime":3880.82,"text":"Good, it'll be hot and sour soup.","speaker":"SPEAKER_05"},{"id":"594","startTime":4188.41,"endTime":4189.44,"text":"What's up?","speaker":"SPEAKER_05"},{"id":"595","startTime":4189.51,"endTime":4192.45,"text":"The teacher wants us at school\nsmelting steel.","speaker":"SPEAKER_05"},{"id":"596","startTime":4192.52,"endTime":4194.68,"text":"The District Head's making an inspection.","speaker":"SPEAKER_05"},{"id":"628","startTime":4321.11,"endTime":4322.54,"text":"And after the ox?","speaker":"SPEAKER_05"},{"id":"1044","startTime":6656.94,"endTime":6659.97,"text":"What's this about pushing?\nToo early for pushing!","speaker":"SPEAKER_05"},{"id":"1045","startTime":6660.41,"endTime":6663.75,"text":"And what's this shouting? Out!","speaker":"SPEAKER_05"},{"id":"1046","startTime":6664.35,"endTime":6666.25,"text":"Go wait in the corridor.","speaker":"SPEAKER_05"},{"id":"1064","startTime":6723.48,"endTime":6726.93,"text":"They're all reactionaries.\nWe've overthrown them.","speaker":"SPEAKER_05"},{"id":"1065","startTime":6727.35,"endTime":6730.61,"text":"Relax. Your wife's fine. We can handle this.","speaker":"SPEAKER_05"},{"id":"1073","startTime":6788.17,"endTime":6791.3,"text":"What is he doing here?\nNo reactionaries allowed!","speaker":"SPEAKER_05"},{"id":"1082","startTime":6823.11,"endTime":6825.41,"text":"The working class is really something!","speaker":"SPEAKER_05"},{"id":"1083","startTime":6825.48,"endTime":6827.91,"text":"Wang Bin, don't make any trouble.","speaker":"SPEAKER_05"},{"id":"1084","startTime":6828.15,"endTime":6829.51,"text":"Don't move.","speaker":"SPEAKER_05"},{"id":"1133","startTime":7085.77,"endTime":7088.43,"text":"Where's the family of Xu Fengxia?","speaker":"SPEAKER_05"},{"id":"1134","startTime":7089.74,"endTime":7091.4,"text":"It's a boy, 7.9 pounds.","speaker":"SPEAKER_05"},{"id":"1136","startTime":7093.78,"endTime":7095.65,"text":"We said it would be fine!","speaker":"SPEAKER_05"},{"id":"1137","startTime":7095.72,"endTime":7098.31,"text":"Comrade, how's my daughter?","speaker":"SPEAKER_05"},{"id":"1142","startTime":7105.56,"endTime":7107.55,"text":"No, there's danger of infection.","speaker":"SPEAKER_05"},{"id":"1152","startTime":7155.61,"endTime":7158.24,"text":"It doesn't matter. We're not done yet.","speaker":"SPEAKER_05"},{"id":"1153","startTime":7158.31,"endTime":7163.27,"text":"Wait outside. When we're finished,\nyou can see her as much as you want.","speaker":"SPEAKER_05"},{"id":"1184","startTime":7307.16,"endTime":7308.92,"text":"Yes, he's a professor.","speaker":"SPEAKER_05"},{"id":"1185","startTime":7309.13,"endTime":7310.69,"text":"He'd know for sure.","speaker":"SPEAKER_05"},{"id":"1209","startTime":7470.19,"endTime":7472.68,"text":"Grandpa! It's crooked again.","speaker":"SPEAKER_05"},{"id":"1214","startTime":7488.31,"endTime":7489.77,"text":"Back already?","speaker":"SPEAKER_05"},{"id":"1215","startTime":7489.84,"endTime":7491.57,"text":"Has Little Bun been a good boy?","speaker":"SPEAKER_05"},{"id":"1216","startTime":7492.11,"endTime":7494.58,"text":"I delivered 10 thermoses of water.","speaker":"SPEAKER_05"},{"id":"1223","startTime":7513.2,"endTime":7514.86,"text":"I light the fire?","speaker":"SPEAKER_05"},{"id":"1224","startTime":7515.9,"endTime":7518.77,"text":"Yes, and I'll make some noodles.","speaker":"SPEAKER_05"},{"id":"1235","startTime":7559.91,"endTime":7562.47,"text":"Grandpa, where will the chicks live?","speaker":"SPEAKER_05"},{"id":"1244","startTime":7601.05,"endTime":7603.78,"text":"Granny, why all the photos for Fengxia?","speaker":"SPEAKER_05"},{"id":"1269","startTime":7706.23,"endTime":7708.79,"text":"Grandpa, where'll we put the chicks?","speaker":"SPEAKER_05"},{"id":"1270","startTime":7710.53,"endTime":7711.89,"text":"Let's see.","speaker":"SPEAKER_05"},{"id":"1276","startTime":7745.33,"endTime":7748.06,"text":"When will they grow up?","speaker":"SPEAKER_05"},{"id":"1277","startTime":7748.47,"endTime":7749.83,"text":"Very soon.","speaker":"SPEAKER_05"},{"id":"1278","startTime":7750.34,"endTime":7751.63,"text":"And then?","speaker":"SPEAKER_05"},{"id":"1286","startTime":7776.5,"endTime":7778.49,"text":"I want to ride on an ox's back!","speaker":"SPEAKER_05"}]}]